Metadata-Version: 2.1
Name: calculator-c08d6d50f5964131
Version: 1000.0.2
Summary: Dependecy Confusion POC
Home-page: UNKNOWN
Author: Henri Williams
Author-email: henri.williams93@gmail.com
License: UNKNOWN
Platform: UNKNOWN
Classifier: Development Status :: 3 - Alpha
Classifier: Intended Audience :: Education
Classifier: Programming Language :: Python :: 2
Classifier: Programming Language :: Python :: 3
Classifier: Operating System :: MacOS :: MacOS X
Classifier: Operating System :: Microsoft :: Windows
